jquery/__init__.py
jquery/static/jquery/jquery-1.11.3.min.js
jquery/static/jquery/jquery-1.12.1.min.js
jquery/static/jquery/jquery-1.12.3.min.js
jquery/static/jquery/jquery-2.2.3.min.js
jquery/static/jquery/jquery-3.2.1.js
jquery/static/jquery/jquery-3.2.1.min.js
jquery/static/jquery/jquery-3.2.1.min.map
jquery/templatetags/__init__.py
jquery/templatetags/jquery.py
static_jquery-3.2.1.0.dist-info/DESCRIPTION.rst
static_jquery-3.2.1.0.dist-info/METADATA
static_jquery-3.2.1.0.dist-info/RECORD
static_jquery-3.2.1.0.dist-info/WHEEL
static_jquery-3.2.1.0.dist-info/metadata.json
static_jquery-3.2.1.0.dist-info/top_level.txt
