Metadata-Version: 2.0
Name: static-jquery
Version: 3.2.1.0
Summary: jQuery packaged in an handy django app to speed up new applications and deployment.
Home-page: https://github.com/wtayyeb/static-jquery
Author: wtayyeb
Author-email: wtayyeb@gmail.com
License: MIT
Keywords: django jquery staticfiles templatetags
Platform: UNKNOWN
Classifier: Development Status :: 5 - Production/Stable
Classifier: Environment :: Web Environment
Classifier: Framework :: Django
Classifier: Intended Audience :: Developers
Classifier: Natural Language :: English
Classifier: License :: OSI Approved :: MIT License
Classifier: Operating System :: OS Independent
Classifier: Programming Language :: Python
Classifier: Topic :: Utilities
Requires-Dist: django-appconf
